ElijeTuPok/__init__.py
ElijeTuPok/pokemon.csv
ElijeTuPok/random_pokemon.py
Snorlax/__init__.py
Snorlax/pokemon.csv
Snorlax/random_pokemon.py
YoteelijSnorlax/__init__.py
YoteelijSnorlax/pokemon.csv
YoteelijSnorlax/random_pokemon.py
ElijeTuPok-1.0.2.dist-info/METADATA
ElijeTuPok-1.0.2.dist-info/WHEEL
ElijeTuPok-1.0.2.dist-info/top_level.txt
ElijeTuPok-1.0.2.dist-info/RECORD
